{
  "getItemList": {
    "data": {
      "total": 19,
      "ItemList": [
        {
          "MATERIAL_QUALITY": "罗敏秀",
          "ITEM_STANDARD": null,
          "EMPLOYEE": null,
          "WRITER": "0",
          "ACCEPTORID": "sykm",
          "BRANDID": null,
          "ABANDON": false,
          "CLIENT": null,
          "CLIENTID": null,
          "REP": null,
          "picDate": null,
          "picName": null,
          "ProductFactoryID": null,
          "picDX": null,
          "picBz": null,
          "ITEM_CLASSID": "SO",
          "SUPPLIERNO": "mtcb001",
          "ITEM_CLASS": "销售",
          "SUPPLIER": "广州铭泰船舶科技有限公司",
          "ITEM_TYPEID": "SO15",
          "MB": null,
          "ABC_CODE": null,
          "ITEM_DATE": "2017-1-17 15:36",
          "Auditor": null,
          "LT": null,
          "SAFETY_STK": null,
          "ITEM_STAT": null,
          "ProductFactory": null,
          "BRAND": null,
          "SERIAL_NUMBER": null,
          "SQEC": "OXILYSER 3",
          "UM": "瓶",
          "ITEM_TYPE": "其他",
          "ITEM_DESC": "钝化膜测试液",
          "ITEM": "SO15-00071",
          "id": "db95227517d2d3f7cdefa5383aeae301"
        },
        {
          "MATERIAL_QUALITY": "罗敏秀",
          "ITEM_STANDARD": null,
          "EMPLOYEE": null,
          "WRITER": "0",
          "ACCEPTORID": "sykm",
          "BRANDID": null,
          "ABANDON": false,
          "CLIENT": null,
          "CLIENTID": null,
          "REP": null,
          "picDate": null,
          "picName": null,
          "ProductFactoryID": null,
          "picDX": null,
          "picBz": null,
          "ITEM_CLASSID": "SO",
          "SUPPLIERNO": null,
          "ITEM_CLASS": "销售",
          "SUPPLIER": null,
          "ITEM_TYPEID": "SO15",
          "MB": null,
          "ABC_CODE": null,
          "ITEM_DATE": "2017-1-7 15:18",
          "Auditor": null,
          "LT": null,
          "SAFETY_STK": null,
          "ITEM_STAT": null,
          "ProductFactory": null,
          "BRAND": null,
          "SERIAL_NUMBER": null,
          "SQEC": null,
          "UM": null,
          "ITEM_TYPE": "其他",
          "ITEM_DESC": "红外线测温仪检测",
          "ITEM": "SO15-00070",
          "id": "1c15f4b2a37ec676695f190bda3fb5f8"
        },
        {
          "MATERIAL_QUALITY": "陈婉莹",
          "ITEM_STANDARD": null,
          "EMPLOYEE": null,
          "WRITER": "0",
          "ACCEPTORID": "mtcb",
          "BRANDID": null,
          "ABANDON": false,
          "CLIENT": null,
          "CLIENTID": null,
          "REP": null,
          "picDate": null,
          "picName": null,
          "ProductFactoryID": null,
          "picDX": null,
          "picBz": null,
          "ITEM_CLASSID": "SO",
          "SUPPLIERNO": "SHSN0005",
          "ITEM_CLASS": "销售",
          "SUPPLIER": "上海善能机械有限公司",
          "ITEM_TYPEID": "SO15",
          "MB": null,
          "ABC_CODE": null,
          "ITEM_DATE": "2017-1-18 14:42",
          "Auditor": null,
          "LT": null,
          "SAFETY_STK": null,
          "ITEM_STAT": null,
          "ProductFactory": null,
          "BRAND": null,
          "SERIAL_NUMBER": null,
          "SQEC": "U22J63",
          "UM": "PCS",
          "ITEM_TYPE": "其他",
          "ITEM_DESC": "油石",
          "ITEM": "SO15-00046",
          "id": "cab76e5ba11ff3df237b0b418c3c7107"
        },
        {
          "MATERIAL_QUALITY": "陈婉莹",
          "ITEM_STANDARD": null,
          "EMPLOYEE": null,
          "WRITER": "0",
          "ACCEPTORID": "mtcb",
          "BRANDID": null,
          "ABANDON": false,
          "CLIENT": null,
          "CLIENTID": null,
          "REP": null,
          "picDate": null,
          "picName": null,
          "ProductFactoryID": null,
          "picDX": null,
          "picBz": null,
          "ITEM_CLASSID": "SO",
          "SUPPLIERNO": null,
          "ITEM_CLASS": "销售",
          "SUPPLIER": null,
          "ITEM_TYPEID": "SO15",
          "MB": null,
          "ABC_CODE": null,
          "ITEM_DATE": "2017-1-12 14:25",
          "Auditor": null,
          "LT": null,
          "SAFETY_STK": null,
          "ITEM_STAT": null,
          "ProductFactory": null,
          "BRAND": null,
          "SERIAL_NUMBER": null,
          "SQEC": "Φ50*60mm",
          "UM": "个",
          "ITEM_TYPE": "其他",
          "ITEM_DESC": "双头压辊小压滚",
          "ITEM": "SO15-00045",
          "id": "580c80db73a83b7992cd25659af55bd5"
        },
        {
          "MATERIAL_QUALITY": "王淑红",
          "ITEM_STANDARD": null,
          "EMPLOYEE": null,
          "WRITER": "0",
          "ACCEPTORID": "mtcb",
          "BRANDID": null,
          "ABANDON": false,
          "CLIENT": null,
          "CLIENTID": null,
          "REP": null,
          "picDate": null,
          "picName": null,
          "ProductFactoryID": null,
          "picDX": null,
          "picBz": null,
          "ITEM_CLASSID": "SO",
          "SUPPLIERNO": "GCGJ001",
          "ITEM_CLASS": "销售",
          "SUPPLIER": "广船国际有限公司",
          "ITEM_TYPEID": "SO15",
          "MB": null,
          "ABC_CODE": null,
          "ITEM_DATE": "2017-1-7 16:13",
          "Auditor": null,
          "LT": null,
          "SAFETY_STK": null,
          "ITEM_STAT": null,
          "ProductFactory": null,
          "BRAND": null,
          "SERIAL_NUMBER": null,
          "SQEC": null,
          "UM": null,
          "ITEM_TYPE": "其他",
          "ITEM_DESC": "恒温槽检测费",
          "ITEM": "SO15-00044",
          "id": "544a751982eaea37a374a40243a06537"
        },
        {
          "MATERIAL_QUALITY": "陈婉莹",
          "ITEM_STANDARD": null,
          "EMPLOYEE": null,
          "WRITER": "0",
          "ACCEPTORID": "mtcb",
          "BRANDID": null,
          "ABANDON": false,
          "CLIENT": null,
          "CLIENTID": null,
          "REP": null,
          "picDate": null,
          "picName": null,
          "ProductFactoryID": null,
          "picDX": null,
          "picBz": null,
          "ITEM_CLASSID": "SO",
          "SUPPLIERNO": null,
          "ITEM_CLASS": "销售",
          "SUPPLIER": null,
          "ITEM_TYPEID": "SO15",
          "MB": null,
          "ABC_CODE": null,
          "ITEM_DATE": "2017-1-7 9:19",
          "Auditor": null,
          "LT": null,
          "SAFETY_STK": null,
          "ITEM_STAT": null,
          "ProductFactory": null,
          "BRAND": null,
          "SERIAL_NUMBER": null,
          "SQEC": "130*190MM 100页/本",
          "UM": "本",
          "ITEM_TYPE": "其他",
          "ITEM_DESC": "报损单",
          "ITEM": "SO15-00043",
          "id": "19b0e49b725d668266bf04b238062fa8"
        },
        {
          "MATERIAL_QUALITY": "陈婉莹",
          "ITEM_STANDARD": null,
          "EMPLOYEE": null,
          "WRITER": "0",
          "ACCEPTORID": "mtcb",
          "BRANDID": null,
          "ABANDON": false,
          "CLIENT": null,
          "CLIENTID": null,
          "REP": null,
          "picDate": null,
          "picName": null,
          "ProductFactoryID": null,
          "picDX": null,
          "picBz": null,
          "ITEM_CLASSID": "SO",
          "SUPPLIERNO": null,
          "ITEM_CLASS": "销售",
          "SUPPLIER": null,
          "ITEM_TYPEID": "SO15",
          "MB": null,
          "ABC_CODE": null,
          "ITEM_DATE": "2017-1-7 9:19",
          "Auditor": null,
          "LT": null,
          "SAFETY_STK": null,
          "ITEM_STAT": null,
          "ProductFactory": null,
          "BRAND": null,
          "SERIAL_NUMBER": null,
          "SQEC": "420*290mm",
          "UM": "张",
          "ITEM_TYPE": "其他",
          "ITEM_DESC": "离心机运行记录表",
          "ITEM": "SO15-00042",
          "id": "325a44e54fda63282256eeebcaa54827"
        },
        {
          "MATERIAL_QUALITY": "陈婉莹",
          "ITEM_STANDARD": null,
          "EMPLOYEE": null,
          "WRITER": "0",
          "ACCEPTORID": "mtcb",
          "BRANDID": null,
          "ABANDON": false,
          "CLIENT": null,
          "CLIENTID": null,
          "REP": null,
          "picDate": null,
          "picName": null,
          "ProductFactoryID": null,
          "picDX": null,
          "picBz": null,
          "ITEM_CLASSID": "SO",
          "SUPPLIERNO": null,
          "ITEM_CLASS": "销售",
          "SUPPLIER": null,
          "ITEM_TYPEID": "SO15",
          "MB": null,
          "ABC_CODE": null,
          "ITEM_DATE": "2017-1-7 9:18",
          "Auditor": null,
          "LT": null,
          "SAFETY_STK": null,
          "ITEM_STAT": null,
          "ProductFactory": null,
          "BRAND": null,
          "SERIAL_NUMBER": null,
          "SQEC": "附样 100页/本",
          "UM": "本",
          "ITEM_TYPE": "其他",
          "ITEM_DESC": "工具借用单",
          "ITEM": "SO15-00041",
          "id": "ffd210f5127a8c216d7117b513aa4a38"
        },
        {
          "MATERIAL_QUALITY": "陈婉莹",
          "ITEM_STANDARD": null,
          "EMPLOYEE": null,
          "WRITER": "0",
          "ACCEPTORID": "mtcb",
          "BRANDID": null,
          "ABANDON": false,
          "CLIENT": null,
          "CLIENTID": null,
          "REP": null,
          "picDate": null,
          "picName": null,
          "ProductFactoryID": null,
          "picDX": null,
          "picBz": null,
          "ITEM_CLASSID": "SO",
          "SUPPLIERNO": null,
          "ITEM_CLASS": "销售",
          "SUPPLIER": null,
          "ITEM_TYPEID": "SO15",
          "MB": null,
          "ABC_CODE": null,
          "ITEM_DATE": "2017-1-7 9:18",
          "Auditor": null,
          "LT": null,
          "SAFETY_STK": null,
          "ITEM_STAT": null,
          "ProductFactory": null,
          "BRAND": null,
          "SERIAL_NUMBER": null,
          "SQEC": "附样 100页/本",
          "UM": "本",
          "ITEM_TYPE": "其他",
          "ITEM_DESC": "低值易耗品报损单",
          "ITEM": "SO15-00040",
          "id": "31341795d2528abe3390b571bb7449b9"
        },
        {
          "MATERIAL_QUALITY": "王淑红",
          "ITEM_STANDARD": null,
          "EMPLOYEE": null,
          "WRITER": "0",
          "ACCEPTORID": "sykm",
          "BRANDID": null,
          "ABANDON": false,
          "CLIENT": null,
          "CLIENTID": null,
          "REP": null,
          "picDate": null,
          "picName": null,
          "ProductFactoryID": null,
          "picDX": null,
          "picBz": null,
          "ITEM_CLASSID": "SO",
          "SUPPLIERNO": null,
          "ITEM_CLASS": "销售",
          "SUPPLIER": null,
          "ITEM_TYPEID": "SO15",
          "MB": null,
          "ABC_CODE": null,
          "ITEM_DATE": "2017-1-5 9:21",
          "Auditor": null,
          "LT": null,
          "SAFETY_STK": null,
          "ITEM_STAT": null,
          "ProductFactory": null,
          "BRAND": null,
          "SERIAL_NUMBER": null,
          "SQEC": "PX-20 红色",
          "UM": "支",
          "ITEM_TYPE": "其他",
          "ITEM_DESC": "记号笔",
          "ITEM": "SO15-00039",
          "id": "594319fa2a8b6a2fe656ae246357a9ef"
        },
        {
          "MATERIAL_QUALITY": "王淑红",
          "ITEM_STANDARD": null,
          "EMPLOYEE": null,
          "WRITER": "0",
          "ACCEPTORID": "sykm",
          "BRANDID": null,
          "ABANDON": false,
          "CLIENT": null,
          "CLIENTID": null,
          "REP": null,
          "picDate": null,
          "picName": null,
          "ProductFactoryID": null,
          "picDX": null,
          "picBz": null,
          "ITEM_CLASSID": "SO",
          "SUPPLIERNO": null,
          "ITEM_CLASS": "销售",
          "SUPPLIER": null,
          "ITEM_TYPEID": "SO15",
          "MB": null,
          "ABC_CODE": null,
          "ITEM_DATE": "2017-1-5 9:20",
          "Auditor": null,
          "LT": null,
          "SAFETY_STK": null,
          "ITEM_STAT": null,
          "ProductFactory": null,
          "BRAND": null,
          "SERIAL_NUMBER": null,
          "SQEC": "PX-20 白色",
          "UM": "支",
          "ITEM_TYPE": "其他",
          "ITEM_DESC": "记号笔",
          "ITEM": "SO15-00038",
          "id": "8da0dd60e9c442963b38a11ff0136750"
        },
        {
          "MATERIAL_QUALITY": "系统管理员",
          "ITEM_STANDARD": null,
          "EMPLOYEE": null,
          "WRITER": "0",
          "ACCEPTORID": "sykm",
          "BRANDID": null,
          "ABANDON": false,
          "CLIENT": null,
          "CLIENTID": null,
          "REP": null,
          "picDate": null,
          "picName": null,
          "ProductFactoryID": null,
          "picDX": null,
          "picBz": null,
          "ITEM_CLASSID": "SO",
          "SUPPLIERNO": null,
          "ITEM_CLASS": "销售",
          "SUPPLIER": null,
          "ITEM_TYPEID": "SO15",
          "MB": null,
          "ABC_CODE": null,
          "ITEM_DATE": null,
          "Auditor": null,
          "LT": null,
          "SAFETY_STK": null,
          "ITEM_STAT": null,
          "ProductFactory": null,
          "BRAND": null,
          "SERIAL_NUMBER": null,
          "SQEC": "\\",
          "UM": "卷",
          "ITEM_TYPE": "其他",
          "ITEM_DESC": "布基胶带",
          "ITEM": "SO15-00009",
          "id": "2c908082594ffb9001595000ddc20c4b"
        },
        {
          "MATERIAL_QUALITY": "系统管理员",
          "ITEM_STANDARD": null,
          "EMPLOYEE": null,
          "WRITER": "0",
          "ACCEPTORID": "sykm",
          "BRANDID": null,
          "ABANDON": false,
          "CLIENT": null,
          "CLIENTID": null,
          "REP": null,
          "picDate": null,
          "picName": null,
          "ProductFactoryID": null,
          "picDX": null,
          "picBz": null,
          "ITEM_CLASSID": "SO",
          "SUPPLIERNO": null,
          "ITEM_CLASS": "销售",
          "SUPPLIER": null,
          "ITEM_TYPEID": "SO15",
          "MB": null,
          "ABC_CODE": null,
          "ITEM_DATE": null,
          "Auditor": null,
          "LT": null,
          "SAFETY_STK": null,
          "ITEM_STAT": null,
          "ProductFactory": null,
          "BRAND": null,
          "SERIAL_NUMBER": null,
          "SQEC": "oks 1110",
          "UM": "支",
          "ITEM_TYPE": "其他",
          "ITEM_DESC": "润滑脂",
          "ITEM": "SO15-00008",
          "id": "2c908082594ffb9001595000ddc20c4a"
        },
        {
          "MATERIAL_QUALITY": "陈婉莹",
          "ITEM_STANDARD": null,
          "EMPLOYEE": null,
          "WRITER": "0",
          "ACCEPTORID": "mtcb",
          "BRANDID": null,
          "ABANDON": false,
          "CLIENT": null,
          "CLIENTID": null,
          "REP": null,
          "picDate": null,
          "picName": null,
          "ProductFactoryID": null,
          "picDX": null,
          "picBz": null,
          "ITEM_CLASSID": "SO",
          "SUPPLIERNO": null,
          "ITEM_CLASS": "销售",
          "SUPPLIER": null,
          "ITEM_TYPEID": "SO13",
          "MB": null,
          "ABC_CODE": null,
          "ITEM_DATE": "2017-1-19 14:23",
          "Auditor": null,
          "LT": null,
          "SAFETY_STK": null,
          "ITEM_STAT": null,
          "ProductFactory": null,
          "BRAND": null,
          "SERIAL_NUMBER": null,
          "SQEC": "（0-9）5MM",
          "UM": "套",
          "ITEM_TYPE": "配件",
          "ITEM_DESC": "数字字码",
          "ITEM": "SO13-00182",
          "id": "c00f5de57dfdd799f3b64e1ccfd8a77d"
        },
        {
          "MATERIAL_QUALITY": "王淑红",
          "ITEM_STANDARD": null,
          "EMPLOYEE": null,
          "WRITER": "0",
          "ACCEPTORID": "mtcb",
          "BRANDID": null,
          "ABANDON": false,
          "CLIENT": null,
          "CLIENTID": null,
          "REP": null,
          "picDate": null,
          "picName": null,
          "ProductFactoryID": null,
          "picDX": null,
          "picBz": null,
          "ITEM_CLASSID": "SO",
          "SUPPLIERNO": "BEJBJHC001",
          "ITEM_CLASS": "销售",
          "SUPPLIER": "北京宏畅航宇仪器仪表有限公司",
          "ITEM_TYPEID": "SO13",
          "MB": null,
          "ABC_CODE": null,
          "ITEM_DATE": "2017-1-19 13:44",
          "Auditor": null,
          "LT": null,
          "SAFETY_STK": null,
          "ITEM_STAT": null,
          "ProductFactory": null,
          "BRAND": null,
          "SERIAL_NUMBER": null,
          "SQEC": "TCR1202(872584)",
          "UM": "台",
          "ITEM_TYPE": "配件",
          "ITEM_DESC": "全站仪配件",
          "ITEM": "SO13-00181",
          "id": "6e0bfaf96ac79b5272f5fb05c5c07a12"
        },
        {
          "MATERIAL_QUALITY": "王淑红",
          "ITEM_STANDARD": null,
          "EMPLOYEE": null,
          "WRITER": "0",
          "ACCEPTORID": "mtcb",
          "BRANDID": null,
          "ABANDON": false,
          "CLIENT": null,
          "CLIENTID": null,
          "REP": null,
          "picDate": null,
          "picName": null,
          "ProductFactoryID": null,
          "picDX": null,
          "picBz": null,
          "ITEM_CLASSID": "SO",
          "SUPPLIERNO": "SHLY0041",
          "ITEM_CLASS": "销售",
          "SUPPLIER": "上海龙禹船舶技术有限公司",
          "ITEM_TYPEID": "SO13",
          "MB": null,
          "ABC_CODE": null,
          "ITEM_DATE": "2017-1-18 14:24",
          "Auditor": null,
          "LT": null,
          "SAFETY_STK": null,
          "ITEM_STAT": null,
          "ProductFactory": null,
          "BRAND": null,
          "SERIAL_NUMBER": null,
          "SQEC": null,
          "UM": "个",
          "ITEM_TYPE": "配件",
          "ITEM_DESC": "旋转标靶",
          "ITEM": "SO13-00180",
          "id": "b4c6103b73ff63b3b04c27a0d6c1f338"
        },
        {
          "MATERIAL_QUALITY": "王淑红",
          "ITEM_STANDARD": null,
          "EMPLOYEE": null,
          "WRITER": "0",
          "ACCEPTORID": "mtcb",
          "BRANDID": null,
          "ABANDON": false,
          "CLIENT": null,
          "CLIENTID": null,
          "REP": null,
          "picDate": null,
          "picName": null,
          "ProductFactoryID": null,
          "picDX": null,
          "picBz": null,
          "ITEM_CLASSID": "SO",
          "SUPPLIERNO": null,
          "ITEM_CLASS": "销售",
          "SUPPLIER": null,
          "ITEM_TYPEID": "SO13",
          "MB": null,
          "ABC_CODE": null,
          "ITEM_DATE": "2017-1-16 11:51",
          "Auditor": null,
          "LT": null,
          "SAFETY_STK": null,
          "ITEM_STAT": null,
          "ProductFactory": null,
          "BRAND": null,
          "SERIAL_NUMBER": null,
          "SQEC": "FX101 (CE0406)",
          "UM": "套",
          "ITEM_TYPE": "配件",
          "ITEM_DESC": "进口全站仪目镜组",
          "ITEM": "SO13-00179",
          "id": "2710ffec5cbc978280a3536db299e8d5"
        },
        {
          "MATERIAL_QUALITY": "王淑红",
          "ITEM_STANDARD": null,
          "EMPLOYEE": null,
          "WRITER": "0",
          "ACCEPTORID": "mtcb",
          "BRANDID": null,
          "ABANDON": false,
          "CLIENT": null,
          "CLIENTID": null,
          "REP": null,
          "picDate": null,
          "picName": null,
          "ProductFactoryID": null,
          "picDX": null,
          "picBz": null,
          "ITEM_CLASSID": "SO",
          "SUPPLIERNO": null,
          "ITEM_CLASS": "销售",
          "SUPPLIER": null,
          "ITEM_TYPEID": "SO13",
          "MB": null,
          "ABC_CODE": null,
          "ITEM_DATE": "2017-1-16 11:51",
          "Auditor": null,
          "LT": null,
          "SAFETY_STK": null,
          "ITEM_STAT": null,
          "ProductFactory": null,
          "BRAND": null,
          "SERIAL_NUMBER": null,
          "SQEC": "FX101 (CE0406)",
          "UM": "个",
          "ITEM_TYPE": "配件",
          "ITEM_DESC": "进口全站仪测距接收板",
          "ITEM": "SO13-00178",
          "id": "9766775386ce7625ec7e66216e83a0ba"
        },
        {
          "MATERIAL_QUALITY": "王淑红",
          "ITEM_STANDARD": null,
          "EMPLOYEE": null,
          "WRITER": "0",
          "ACCEPTORID": "mtcb",
          "BRANDID": null,
          "ABANDON": false,
          "CLIENT": null,
          "CLIENTID": null,
          "REP": null,
          "picDate": null,
          "picName": null,
          "ProductFactoryID": null,
          "picDX": null,
          "picBz": null,
          "ITEM_CLASSID": "SO",
          "SUPPLIERNO": null,
          "ITEM_CLASS": "销售",
          "SUPPLIER": null,
          "ITEM_TYPEID": "SO13",
          "MB": null,
          "ABC_CODE": null,
          "ITEM_DATE": "2017-1-16 11:50",
          "Auditor": null,
          "LT": null,
          "SAFETY_STK": null,
          "ITEM_STAT": null,
          "ProductFactory": null,
          "BRAND": null,
          "SERIAL_NUMBER": null,
          "SQEC": "FX101 (CE0406)",
          "UM": "套",
          "ITEM_TYPE": "配件",
          "ITEM_DESC": "进口全站仪横轴",
          "ITEM": "SO13-00177",
          "id": "8ef4a1a4fd7cf41e52f6da52117c73e7"
        }
      ]
    },
    "msg": "",
    "success": true
  }
}
